LICENSE
MANIFEST.in
README.md
install.json
package.json
pyproject.toml
setup.py
tsconfig.json
JLTomorrowNight/__init__.py
JLTomorrowNight/_version.py
JLTomorrowNight.egg-info/PKG-INFO
JLTomorrowNight.egg-info/SOURCES.txt
JLTomorrowNight.egg-info/dependency_links.txt
JLTomorrowNight.egg-info/not-zip-safe
JLTomorrowNight.egg-info/requires.txt
JLTomorrowNight.egg-info/top_level.txt
JLTomorrowNight/labextension/package.json
JLTomorrowNight/labextension/static/534.85eb7a25a1a5420942d3.js
JLTomorrowNight/labextension/static/568.27ab0d4bd2b49f59308d.js
JLTomorrowNight/labextension/static/remoteEntry.d803338cb97f4679b976.js
JLTomorrowNight/labextension/static/style.js
JLTomorrowNight/labextension/themes/JLTomorrowNight/index.css
JLTomorrowNight/labextension/themes/JLTomorrowNight/index.js
src/index.ts
style/base.css
style/fonts.css
style/index.css
style/index.js
style/variables.css
style/fonts/FiraCode-Bold.ttf
style/fonts/FiraCode-Regular.ttf