Metadata-Version: 2.1
Name: JLTomorrowNight
Version: 0.2.0
Summary: Tomorrow Theme
Home-page: https://github.com/karosc/JLTomorrowNight
Author: karosc
Author-email: ckaros@outlook.com
License: BSD-3-Clause
Keywords: Jupyter,JupyterLab,JupyterLab3
Platform: Linux
Platform: Mac OS X
Platform: Windows
Classifier: License :: OSI Approved :: BSD License
Classifier: Programming Language :: Python
Classifier: Programming Language :: Python :: 3
Classifier: Programming Language :: Python :: 3.6
Classifier: Programming Language :: Python :: 3.7
Classifier: Programming Language :: Python :: 3.8
Classifier: Programming Language :: Python :: 3.9
Classifier: Framework :: Jupyter
Requires-Python: >=3.6
